LICENSE.txt
MANIFEST.in
README.rst
setup.py
scrivener/__init__.py
scrivener/client.py
scrivener/handlers.py
scrivener/interfaces.py
scrivener/server.py
scrivener/tap.py
scrivener.egg-info/PKG-INFO
scrivener.egg-info/SOURCES.txt
scrivener.egg-info/dependency_links.txt
scrivener.egg-info/requires.txt
scrivener.egg-info/top_level.txt
scrivener/_thrift/__init__.py
scrivener/_thrift/scribe.thrift
scrivener/_thrift/scribe/__init__.py
scrivener/_thrift/scribe/constants.py
scrivener/_thrift/scribe/scribe-remote
scrivener/_thrift/scribe/scribe.py
scrivener/_thrift/scribe/ttypes.py
scrivener/tests/__init__.py
scrivener/tests/test_client.py
scrivener/tests/test_handlers.py
scrivener/tests/test_server.py
twisted/plugins/scribe_tap.py