Metadata-Version: 1.0
Name: scrivener
Version: 0.2
Summary: Twisted Scribe Client/Server
Home-page: https://github.com/racker/scrivener/
Author: David Reid
Author-email: david.reid@rackspace.com
License: APL2
Platform: UNKNOWN
Classifier: Development Status :: 4 - Beta
Classifier: License :: OSI Approved :: Apache Software License
Classifier: Programming Language :: Python :: 2.7
Classifier: Framework :: Twisted
